niaussat/niaussat/__init__.py
niaussat/pyproject.toml
niaussat/README.md
niaussat/tests/__init__.py
niaussat-0.1.0.dist-info/entry_points.txt
niaussat-0.1.0.dist-info/METADATA
niaussat-0.1.0.dist-info/WHEEL
niaussat-0.1.0.dist-info/RECORD
