Metadata-Version: 2.3
Name: niaussat
Version: 0.1.0
Summary: Niaussat, the new math package for complex calculus
License: MIT
Keywords: math,calculus,complex,mathematics,science
Author: Your Name
Author-email: you@example.com
Maintainer: Your Name
Maintainer-email: you@example.com
Requires-Python: >=3.10
Classifier: License :: OSI Approved :: MIT License
Classifier: Programming Language :: Python :: 3
Classifier: Programming Language :: Python :: 3.10
Classifier: Programming Language :: Python :: 3.11
Classifier: Programming Language :: Python :: 3.12
Classifier: Programming Language :: Python :: 3.13
Requires-Dist: numpy (>=1.21.0)
